LICENSE
README.rst
setup.cfg
setup.py
dandelion/__init__.py
dandelion/base.py
dandelion/datagem.py
dandelion/datatxt.py
dandelion/utils.py
dandelion/cache/__init__.py
dandelion/cache/base.py
dandelion/cache/file.py
dandelion_eu.egg-info/PKG-INFO
dandelion_eu.egg-info/SOURCES.txt
dandelion_eu.egg-info/dependency_links.txt
dandelion_eu.egg-info/requires.txt
dandelion_eu.egg-info/top_level.txt