Metadata-Version: 2.1
Name: dandelion-eu
Version: 0.3.3
Summary: Connect to the dandelion.eu API in a very pythonic way!
Home-page: https://github.com/giacbrd/python-dandelion-eu
Download-URL: https://github.com/giacbrd/python-dandelion-eu/tarball/0.3.3
Author: SpazioDati s.r.l.
Author-email: berardi@spaziodati.eu
Keywords: api,dandelion
Classifier: Intended Audience :: Developers
Classifier: Topic :: Scientific/Engineering :: Artificial Intelligence
Classifier: Topic :: Scientific/Engineering :: Information Analysis
Classifier: Topic :: Text Processing :: Linguistic
Classifier: Natural Language :: English
Classifier: Natural Language :: Italian
Classifier: Natural Language :: Spanish
Classifier: Natural Language :: French
Classifier: Natural Language :: German
Classifier: Natural Language :: Russian
Classifier: Natural Language :: Portuguese
Classifier: Programming Language :: Python
Classifier: Programming Language :: Python :: 2
Classifier: Programming Language :: Python :: 2.7
Classifier: Programming Language :: Python :: 3
Classifier: Programming Language :: Python :: 3.2
Classifier: Programming Language :: Python :: 3.3
Classifier: Programming Language :: Python :: 3.4
Classifier: Programming Language :: Python :: 3.5
Classifier: Programming Language :: Python :: 3.6
Classifier: Programming Language :: Python :: 3.7
License-File: LICENSE
